GasolinaMexicoScrapper/__init__.py
GasolinaMexicoScrapper/exceptions.py
GasolinaMexicoScrapper/scrapper.py
GasolinaMexicoScrapper-0.1.0.dist-info/LICENSE
GasolinaMexicoScrapper-0.1.0.dist-info/METADATA
GasolinaMexicoScrapper-0.1.0.dist-info/WHEEL
GasolinaMexicoScrapper-0.1.0.dist-info/top_level.txt
GasolinaMexicoScrapper-0.1.0.dist-info/RECORD
