Metadata-Version: 2.1
Name: GasolinaMexicoScrapper
Version: 0.1.0
Summary: A example Python package
Home-page: https://github.com/R3SWebDevelopment/GasolinaMexicoScrapper
Author: Ricardo Tercero Solis
Author-email: ricardo.tercero@r3s.com.mx
License: BSD 2-clause
Platform: UNKNOWN
Classifier: Development Status :: 1 - Planning
Classifier: Intended Audience :: Science/Research
Classifier: License :: OSI Approved :: MIT License
Classifier: Operating System :: POSIX :: Linux
Classifier: Programming Language :: Python :: 3
Classifier: Programming Language :: Python :: 3.4
Classifier: Programming Language :: Python :: 3.5
Classifier: Programming Language :: Python :: 3.8
License-File: LICENSE
Requires-Dist: requests (==2.28.2)
Requires-Dist: beautifulsoup4 (==4.11.1)
